NiukeCGangweiMianshiZhentiBaodian20212022Fix1/README.md
NiukeCGangweiMianshiZhentiBaodian20212022Fix1/__init__.py
NiukeCGangweiMianshiZhentiBaodian20212022Fix1/__main__.py
NiukeCGangweiMianshiZhentiBaodian20212022Fix1/file.epub
NiukeCGangweiMianshiZhentiBaodian20212022Fix1/index.html
NiukeCGangweiMianshiZhentiBaodian20212022Fix1/css/__init__.py
NiukeCGangweiMianshiZhentiBaodian20212022Fix1/css/annotations.css
NiukeCGangweiMianshiZhentiBaodian20212022Fix1/css/main.css
NiukeCGangweiMianshiZhentiBaodian20212022Fix1/css/normalize.css
NiukeCGangweiMianshiZhentiBaodian20212022Fix1/css/popup.css
NiukeCGangweiMianshiZhentiBaodian20212022Fix1/font/__init__.py
NiukeCGangweiMianshiZhentiBaodian20212022Fix1/font/fontello.eot
NiukeCGangweiMianshiZhentiBaodian20212022Fix1/font/fontello.svg
NiukeCGangweiMianshiZhentiBaodian20212022Fix1/font/fontello.ttf
NiukeCGangweiMianshiZhentiBaodian20212022Fix1/font/fontello.woff
NiukeCGangweiMianshiZhentiBaodian20212022Fix1/img/__init__.py
NiukeCGangweiMianshiZhentiBaodian20212022Fix1/img/annotator-glyph-sprite.png
NiukeCGangweiMianshiZhentiBaodian20212022Fix1/img/annotator-icon-sprite.png
NiukeCGangweiMianshiZhentiBaodian20212022Fix1/img/apple-touch-icon.png
NiukeCGangweiMianshiZhentiBaodian20212022Fix1/img/cancelfullscreen.png
NiukeCGangweiMianshiZhentiBaodian20212022Fix1/img/close.png
NiukeCGangweiMianshiZhentiBaodian20212022Fix1/img/fullscreen.png
NiukeCGangweiMianshiZhentiBaodian20212022Fix1/img/loader.gif
NiukeCGangweiMianshiZhentiBaodian20212022Fix1/img/menu-icon.png
NiukeCGangweiMianshiZhentiBaodian20212022Fix1/img/save.png
NiukeCGangweiMianshiZhentiBaodian20212022Fix1/img/saved.png
NiukeCGangweiMianshiZhentiBaodian20212022Fix1/img/settings-s.png
NiukeCGangweiMianshiZhentiBaodian20212022Fix1/img/settings.png
NiukeCGangweiMianshiZhentiBaodian20212022Fix1/img/star.png
NiukeCGangweiMianshiZhentiBaodian20212022Fix1/js/__init__.py
NiukeCGangweiMianshiZhentiBaodian20212022Fix1/js/epub.js
niuke_c_gangwei_mianshi_zhenti_baodian_2021_2022_fix1-2025.3.25.0.dist-info/METADATA
niuke_c_gangwei_mianshi_zhenti_baodian_2021_2022_fix1-2025.3.25.0.dist-info/WHEEL
niuke_c_gangwei_mianshi_zhenti_baodian_2021_2022_fix1-2025.3.25.0.dist-info/entry_points.txt
niuke_c_gangwei_mianshi_zhenti_baodian_2021_2022_fix1-2025.3.25.0.dist-info/top_level.txt
niuke_c_gangwei_mianshi_zhenti_baodian_2021_2022_fix1-2025.3.25.0.dist-info/RECORD
